spiffing
