Metadata-Version: 1.1
Name: spiffing
Version: 1.1.0
Summary: The gentleman's CSS pre-processor, to convert correct English CSS to American English CSS (and the reverse).
Home-page: https://github.com/plausibility/spiffing.py
Author: plausibility
Author-email: chris@gibsonsec.org
License: MIT
Keywords: css preprocessor markup english jam
Platform: UNKNOWN
Classifier: Development Status :: 4 - Beta
Classifier: Intended Audience :: Developers
Classifier: License :: OSI Approved :: MIT License
Classifier: Operating System :: OS Independent
Classifier: Programming Language :: Python :: 2
Classifier: Topic :: Text Processing
